PNGtoGIF/__init__.py
PNGtoGIF/converter.py
PNGtoGIF-1.0.3.dist-info/LICENSE
PNGtoGIF-1.0.3.dist-info/METADATA
PNGtoGIF-1.0.3.dist-info/WHEEL
PNGtoGIF-1.0.3.dist-info/top_level.txt
PNGtoGIF-1.0.3.dist-info/RECORD
