Metadata-Version: 2.1
Name: PNGtoGIF
Version: 1.0.3
Summary: Test package for distribution
Home-page: UNKNOWN
Author: Eunki7
Author-email: outsider7224@gmail.com
License: UNKNOWN
Keywords: PNGtoGIF,pngtogif
Platform: UNKNOWN
Classifier: Programming Language :: Python :: 3
Classifier: License :: OSI Approved :: MIT License
Classifier: Operating System :: OS Independent
Requires-Python: >=3
Requires-Dist: pillow
